LICENSE.txt
MANIFEST.in
README.md
setup.cfg
setup.py
Lenpy.egg-info/PKG-INFO
Lenpy.egg-info/SOURCES.txt
Lenpy.egg-info/dependency_links.txt
Lenpy.egg-info/requires.txt
Lenpy.egg-info/top_level.txt
art/Lenpy icon.psd
art/icon.png
art/itch.png
art/itch.psd
art/logo.png
art/logo.psd
examples/Instala Len'Py.txt
examples/test_button.py
examples/test_dataManager.py
examples/test_multiple_images_example.py
examples/test_text.py
examples/test_xml_sprite.py
examples/button_example/ButtonExample.PNG
examples/button_example/button_example.fla
examples/button_example/button_example.png
examples/button_example/button_example.xml
examples/button_example/hover.png
examples/button_example/normal.png
examples/button_example/select.png
examples/fonts/arial.ttf
examples/multiple_images_example/down/Ball Down0001.png
examples/multiple_images_example/down/Ball Down0002.png
examples/multiple_images_example/idle/Ball0001.png
examples/multiple_images_example/idle/Ball0002.png
examples/multiple_images_example/idle/Ball0003.png
examples/multiple_images_example/idle/Ball0004.png
examples/multiple_images_example/left/Ball Left0001.png
examples/multiple_images_example/left/Ball Left0002.png
examples/multiple_images_example/right/Ball Right0001.png
examples/multiple_images_example/right/Ball Right0002.png
examples/multiple_images_example/up/Ball Up0001.png
examples/multiple_images_example/up/Ball Up0002.png
examples/xml_sprite_example/No.png
examples/xml_sprite_example/XML sprite promo.png
examples/xml_sprite_example/Yes.png
examples/xml_sprite_example/ball_example.fla
examples/xml_sprite_example/ball_example.png
examples/xml_sprite_example/ball_example.xml
examples/xml_sprite_example/screenshot.png
examples/xml_sprite_example/screenshot00.PNG
lenpy/__init__.py
lenpy/config.py
lenpy/data.py
lenpy/locals.py
lenpy/spritesheet.py
lenpy/system.py
lenpy/text.py
lenpy/tools.py
lenpy/ui.py
lenpy/version.py