Metadata-Version: 2.1
Name: Lenpy
Version: 0.1.1
Summary: Simplify your life
Home-page: https://github.com/QuetzalcoutlDev/Lenpy
Author: Quetzalcoutl
Author-email: quetzalcoult2022@gmail.com
License: LGPL
Classifier: Development Status :: 3 - Alpha
Classifier: Intended Audience :: Developers
Classifier: Topic :: Software Development :: Build Tools
Classifier: License :: OSI Approved :: GNU Library or Lesser General Public License (LGPL)
Classifier: Programming Language :: Python :: 3.6
Classifier: Programming Language :: Python :: 3.7
Classifier: Programming Language :: Python :: 3.8
Classifier: Programming Language :: Python :: 3.9
Classifier: Programming Language :: Python :: 3.10
Requires-Python: >=3.7
License-File: LICENSE.txt
